scode/Bell.wav
scode/__init__.py
scode/dropbox.py
scode/paramiko.py
scode/schedule.py
scode/selenium.py
scode/telegram.py
scode/util.py
scode-0.7.1.dist-info/METADATA
scode-0.7.1.dist-info/WHEEL
scode-0.7.1.dist-info/top_level.txt
scode-0.7.1.dist-info/RECORD
