Metadata-Version: 2.1
Name: scode
Version: 0.7.1
Summary: The Private Package of Showm Company.
Home-page: https://github.com/showm-dev/Standard
Maintainer-email: smchung218@gmail.com
Classifier: Programming Language :: Python :: 3
Classifier: License :: OSI Approved :: MIT License
Classifier: Operating System :: Microsoft :: Windows
Requires-Python: >=3.6
Requires-Dist: selenium ==3.141.0
Requires-Dist: Pillow ==9.5.0
Requires-Dist: urllib3 ==1.26.12
Requires-Dist: fake-useragent ==1.5.1
Requires-Dist: paramiko
Requires-Dist: packaging
Requires-Dist: dropbox
Requires-Dist: python-dateutil
Requires-Dist: requests
Requires-Dist: pyperclip
Requires-Dist: chromedriver-autoinstaller
Requires-Dist: anticaptchaofficial
Requires-Dist: python-anticaptcha
Requires-Dist: feedparser
Requires-Dist: tqdm
Requires-Dist: chardet
Requires-Dist: docx2txt
Requires-Dist: pyautogui
Requires-Dist: python-telegram-bot ==13.15
